odoo/addons/mgmtsystem_manual/README.rst
odoo/addons/mgmtsystem_manual/__init__.py
odoo/addons/mgmtsystem_manual/__manifest__.py
odoo/addons/mgmtsystem_manual/data/mgmtsystem_manual.xml
odoo/addons/mgmtsystem_manual/i18n/de.po
odoo/addons/mgmtsystem_manual/i18n/es.po
odoo/addons/mgmtsystem_manual/i18n/fr.po
odoo/addons/mgmtsystem_manual/i18n/hr_HR.po
odoo/addons/mgmtsystem_manual/i18n/it.po
odoo/addons/mgmtsystem_manual/i18n/lv.po
odoo/addons/mgmtsystem_manual/i18n/mgmtsystem_manual.pot
odoo/addons/mgmtsystem_manual/i18n/nb.po
odoo/addons/mgmtsystem_manual/i18n/nl_NL.po
odoo/addons/mgmtsystem_manual/i18n/nn.po
odoo/addons/mgmtsystem_manual/i18n/pt_BR.po
odoo/addons/mgmtsystem_manual/i18n/sl.po
odoo/addons/mgmtsystem_manual/i18n/sv.po
odoo/addons/mgmtsystem_manual/i18n/th.po
odoo/addons/mgmtsystem_manual/i18n/vi.po
odoo/addons/mgmtsystem_manual/models/__init__.py
odoo/addons/mgmtsystem_manual/models/mgmtsystem_manual.py
odoo/addons/mgmtsystem_manual/readme/CONFIGURE.md
odoo/addons/mgmtsystem_manual/readme/CONTRIBUTORS.md
odoo/addons/mgmtsystem_manual/readme/CREDITS.md
odoo/addons/mgmtsystem_manual/readme/DESCRIPTION.md
odoo/addons/mgmtsystem_manual/readme/HISTORY.md
odoo/addons/mgmtsystem_manual/readme/INSTALL.md
odoo/addons/mgmtsystem_manual/readme/USAGE.md
odoo/addons/mgmtsystem_manual/static/description/icon.png
odoo/addons/mgmtsystem_manual/static/description/index.html
odoo/addons/mgmtsystem_manual/views/document_page.xml
odoo/addons/mgmtsystem_manual/views/mgmtsystem_manual.xml
odoo_addon_mgmtsystem_manual-18.0.1.0.1.dist-info/METADATA
odoo_addon_mgmtsystem_manual-18.0.1.0.1.dist-info/WHEEL
odoo_addon_mgmtsystem_manual-18.0.1.0.1.dist-info/top_level.txt
odoo_addon_mgmtsystem_manual-18.0.1.0.1.dist-info/RECORD
